ban_peers/__init__.py
ban_peers/__main__.py
ban_peers/appdirs.py
ban_peers/config.py
ban_peers/monkey.py
ban_peers/vendor.txt
ban_peers/i18n/__init__.py
ban_peers/i18n/gettext.py
ban_peers/i18n/msgfmt.py
ban_peers/i18n/locale/en/LC_MESSAGES/argparse.po
ban_peers/i18n/locale/zh_CN/LC_MESSAGES/argparse.po
ban_peers/i18n/locale/zh_CN/LC_MESSAGES/banpeers.po
Ban_Peers-1.0.6.dist-info/LICENSE
Ban_Peers-1.0.6.dist-info/METADATA
Ban_Peers-1.0.6.dist-info/WHEEL
Ban_Peers-1.0.6.dist-info/entry_points.txt
Ban_Peers-1.0.6.dist-info/top_level.txt
Ban_Peers-1.0.6.dist-info/zip-safe
Ban_Peers-1.0.6.dist-info/RECORD
