Metadata-Version: 2.1
Name: Ban-Peers
Version: 1.0.6
Summary: Checking & banning BitTorrent leech peers via Web API, remove Ads, working for μTorrent.
Home-page: https://github.com/SeaHOH/ban-peers
Author: SeaHOH
Author-email: seahoh@gmail.com
License: MIT
Keywords: BitTorrent uTorrent anti-leech ban block XunLei anti-Ads
Platform: any
Classifier: Development Status :: 5 - Production/Stable
Classifier: License :: OSI Approved :: MIT License
Classifier: Operating System :: OS Independent
Classifier: Environment :: Console
Classifier: Programming Language :: Python
Classifier: Programming Language :: Python :: 3
Classifier: Topic :: Utilities
Requires-Python: >=3.7
